biblealignlib/__init__.py
biblealignlib/autoalign/Score.py
biblealignlib/autoalign/__init__.py
biblealignlib/autoalign/corpusmapping.py
biblealignlib/autoalign/eflomal.py
biblealignlib/autoalign/mapper.py
biblealignlib/autoalign/reader.py
biblealignlib/autoalign/runeflomal.py
biblealignlib/autoalign/scorer.py
biblealignlib/autoalign/writer.py
biblealignlib/burrito/AlignmentGroup.py
biblealignlib/burrito/AlignmentSet.py
biblealignlib/burrito/AlignmentType.py
biblealignlib/burrito/BadRecord.py
biblealignlib/burrito/BaseToken.py
biblealignlib/burrito/VerseData.py
biblealignlib/burrito/__init__.py
biblealignlib/burrito/alignments.py
biblealignlib/burrito/manager.py
biblealignlib/burrito/source.py
biblealignlib/burrito/target.py
biblealignlib/burrito/util.py
biblealignlib/coverage/Coverage.py
biblealignlib/coverage/__init__.py
biblealignlib/coverage/analyzer.py
biblealignlib/coverage/exporter.py
biblealignlib/coverage/filters.py
biblealignlib/interlinear/__init__.py
biblealignlib/interlinear/reverse.py
biblealignlib/interlinear/token.py
biblealignlib/strongs.py
biblealignlib/util/__init__.py
biblealignlib/util/merger.py
biblealignlib/util/vocab.py
biblealignlib-0.2.5.dist-info/METADATA
biblealignlib-0.2.5.dist-info/WHEEL
biblealignlib-0.2.5.dist-info/licenses/LICENSE
biblealignlib-0.2.5.dist-info/licenses/LICENSE.md
biblealignlib-0.2.5.dist-info/RECORD
