Metadata-Version: 2.4
Name: biblealignlib
Version: 0.2.5
Summary: Code for managing Word-level alignments for Bibles, including both automatic alignments and manually corrected alignments.
License: MIT
License-File: LICENSE
License-File: LICENSE.md
Keywords: Bible,alignment,Bible alignment
Author: Sean Boisen
Author-email: sean.boisen@biblica.com
Requires-Python: >=3.10,<3.14
Classifier: Development Status :: 4 - Beta
Classifier: Intended Audience :: Religion
Classifier: License :: OSI Approved :: MIT License
Classifier: Operating System :: OS Independent
Classifier: Programming Language :: Python :: 3
Classifier: Programming Language :: Python :: 3.10
Classifier: Programming Language :: Python :: 3.11
Classifier: Programming Language :: Python :: 3.12
Classifier: Programming Language :: Python :: 3.13
Classifier: Topic :: Religion
Classifier: Topic :: Software Development :: Libraries :: Python Modules
Requires-Dist: altair (>=5.5.0,<6.0.0)
Requires-Dist: biblelib (==0.3.28)
Requires-Dist: jupyter-ai (>=2.31.6,<3.0.0)
Requires-Dist: jupyter-server-ydoc (>=1.1.0,<2.0.0)
Requires-Dist: jupyterlab (>=4.3.3,<5.0.0)
Requires-Dist: langchain-openai (>=0.3.33,<0.4.0)
Requires-Dist: pandas (>=2.2.3,<3.0.0)
Requires-Dist: python-dotenv (>=1.0.1,<2.0.0)
Requires-Dist: regex (>=2024.11.6,<2025.0.0)
Requires-Dist: unicodecsv (>=0.14.1,<0.15.0)
Project-URL: Repository, https://github.com/Clear-Bible/biblealignlib
